tavolo/__init__.py
tavolo/embeddings.py
tavolo/learning.py
tavolo/seq2vec.py
tavolo-0.8.0.dist-info/LICENSE
tavolo-0.8.0.dist-info/WHEEL
tavolo-0.8.0.dist-info/METADATA
tavolo-0.8.0.dist-info/RECORD
